twpt_cli/__init__.py
twpt_cli/main.py
twpt_cli/request_interpreter.py
twpt_cli/shell.py
twpt_cli/commands/__init__.py
twpt_cli/commands/chat.py
twpt_cli/commands/configure.py
twpt_cli/commands/custom_task.py
twpt_cli/commands/download_evidence.py
twpt_cli/commands/get_pentest.py
twpt_cli/commands/init.py
twpt_cli/commands/keys.py
twpt_cli/commands/list_pentests.py
twpt_cli/commands/memory.py
twpt_cli/commands/plan.py
twpt_cli/commands/schedule_pentest.py
twpt_cli/commands/uninstall.py
twpt_cli/commands/update.py
twpt_cli/commands/version_cmd.py
twpt_cli/commands/watch.py
twpt_cli/commands/watch_task.py
twpt_cli/commands/webui.py
twpt_cli/config/__init__.py
twpt_cli/config/constants.py
twpt_cli/config/credentials.py
twpt_cli/config/memory.py
twpt_cli/config/plans.py
twpt_cli/config/playbooks.py
twpt_cli/sdk/__init__.py
twpt_cli/sdk/grpc_client.py
twpt_cli/sdk/http_client.py
twpt_cli/sdk/models.py
twpt_cli/sdk/pentest.proto
twpt_cli/sdk/pentest_pb2.py
twpt_cli/sdk/pentest_pb2_grpc.py
twpt_cli/webui/__init__.py
twpt_cli/webui/server.py
twpt_cli/webui/static/css/style.css
twpt_cli/webui/static/js/app.js
twpt_cli/webui/templates/index.html
twpt_cli/webui_simple/__init__.py
twpt_cli/webui_simple/static/css/style.css
twpt_cli/webui_simple/static/js/app.js
twpt_cli/webui_simple/templates/index.html
twpt_cli-1.3.2.dist-info/licenses/LICENSE
twpt_cli-1.3.2.dist-info/METADATA
twpt_cli-1.3.2.dist-info/WHEEL
twpt_cli-1.3.2.dist-info/entry_points.txt
twpt_cli-1.3.2.dist-info/top_level.txt
twpt_cli-1.3.2.dist-info/RECORD
