Metadata-Version: 2.4
Name: twpt-cli
Version: 1.3.2
Summary: ThreatWinds Pentest CLI - Command-line tool for managing automated penetration testing
Author-email: ThreatWinds <support@threatwinds.com>
License-Expression: MIT
Project-URL: Homepage, https://github.com/threatwinds/twpt-cli
Project-URL: Documentation, https://github.com/threatwinds/twpt-cli#readme
Project-URL: Repository, https://github.com/threatwinds/twpt-cli
Project-URL: Issues, https://github.com/threatwinds/twpt-cli/issues
Keywords: penetration-testing,security,pentesting,cli,threatwinds,kali-linux
Classifier: Development Status :: 4 - Beta
Classifier: Intended Audience :: Information Technology
Classifier: Intended Audience :: System Administrators
Classifier: Topic :: Security
Classifier: Topic :: System :: Systems Administration
Classifier: Programming Language :: Python :: 3
Classifier: Programming Language :: Python :: 3.8
Classifier: Programming Language :: Python :: 3.9
Classifier: Programming Language :: Python :: 3.10
Classifier: Programming Language :: Python :: 3.11
Classifier: Programming Language :: Python :: 3.12
Classifier: Operating System :: POSIX :: Linux
Classifier: Operating System :: MacOS
Classifier: Environment :: Console
Requires-Python: >=3.8
License-File: LICENSE
Requires-Dist: click>=8.1.0
Requires-Dist: rich>=13.0.0
Requires-Dist: requests>=2.31.0
Requires-Dist: urllib3>=2.0.0
Requires-Dist: grpcio>=1.60.0
Requires-Dist: grpcio-tools>=1.60.0
Requires-Dist: protobuf>=4.25.0
Requires-Dist: pydantic>=2.5.0
Requires-Dist: python-dotenv>=1.0.0
Requires-Dist: distro>=1.8.0
Requires-Dist: python-dateutil>=2.8.0
Requires-Dist: psutil>=5.9.0
Requires-Dist: httpx>=0.25.0
Requires-Dist: prompt-toolkit>=3.0.0
Requires-Dist: flask>=3.0.0
Requires-Dist: flask-cors>=4.0.0
Provides-Extra: dev
Requires-Dist: pytest>=7.0.0; extra == "dev"
Requires-Dist: pytest-cov>=4.0.0; extra == "dev"
Requires-Dist: black>=23.0.0; extra == "dev"
Requires-Dist: flake8>=6.0.0; extra == "dev"
Requires-Dist: mypy>=1.0.0; extra == "dev"
Provides-Extra: production
Requires-Dist: gunicorn>=21.0.0; extra == "production"
Requires-Dist: gevent>=23.0.0; extra == "production"
Dynamic: license-file
